src/pc.v
/* 5-bit program counter */

module pc(
  input clk_i,
  input rst_i,
  input jmp_en_i,
  input [4:0] jmp_addr_i,
  output reg [4:0] addr_o
);

  always @(posedge clk_i) begin
    if (rst_i)          addr_o <= 5'b0;
    else if (jmp_en_i)  addr_o <= jmp_addr_i;
    else                addr_o <= addr_o + 1;
  end

endmodule

test/pc_tb.v
`include "src/pc.v"

module pc_tb;

  reg clk = 1'b0;
  reg rst = 1'b0;
  reg jmp_en = 1'b0;
  reg [4:0] jmp_addr = 5'b0;

  wire [4:0] curr_addr;

  integer test_idx = 0;

  pc UUT(
    .clk_i(clk), .rst_i(rst), .jmp_en_i(jmp_en), .jmp_addr_i(jmp_addr),
    .addr_o(curr_addr)
  );

  always begin
    clk = ~clk; #5;
  end

  initial begin
    $dumpfile("bin/pc.vcd");
    $dumpvars(0, pc_tb);

 // Inicio de Señales
    $display("-- Inicia Simulación --");
    $display("-----------------------------------------------");
    $display("|            Test   Reset   Jmp   Registro PC |");
    $display("-----------------------------------------------");


    // reset
    rst = 1'b1;
    jmp_en = 1'b0;
    #10;  // delay de 10 unidades de tiempo (tiempo de reloj)
    test_idx++;
    $display("|   %d       %d      %d       %d       |", test_idx, rst, jmp_en, curr_addr);
    
    // not reset
    rst = 0;
    jmp_en = 0;
    #10; test_idx++;
    $display("|   %d       %d      %d       %d       |", test_idx, rst, jmp_en, curr_addr);
    
    #10; test_idx++;
    $display("|   %d       %d      %d       %d       |", test_idx, rst, jmp_en, curr_addr);

    #10; test_idx++;
    $display("|   %d       %d      %d       %d       |", test_idx, rst, jmp_en, curr_addr);

    // jump
    rst = 0;
    jmp_en = 1;  // mientras este en 1, el PC se va a mover a la direccion jmp_addr   
    jmp_addr = 5'b11001;  //19h 25d
    #10; test_idx++;  // 
    $display("|   %d       %d      %d       %d       |", test_idx, rst, jmp_en, curr_addr);

    // reset
    rst = 1;
    jmp_en = 0;
    #10; test_idx++;
    $display("|   %d       %d      %d       %d       |", test_idx, rst, jmp_en, curr_addr);

    // not reset
    rst = 0;
    jmp_en = 0;
    #10; test_idx++;
    $display("|   %d       %d      %d       %d       |", test_idx, rst, jmp_en, curr_addr);
    
    #10; test_idx++;
    $display("|   %d       %d      %d       %d       |", test_idx, rst, jmp_en, curr_addr);

    $display("-----------------------------------------------");

    $display("-- Testbench completed --");
    $finish;

  end

endmodule

bin/pc.vcd
$date
	Wed Jun 12 14:50:32 2024
$end
$version
	Icarus Verilog
$end
$timescale
	1s
$end
$scope module pc_tb $end
$var wire 5 ! curr_addr [4:0] $end
$var reg 1 " clk $end
$var reg 5 # jmp_addr [4:0] $end
$var reg 1 $ jmp_en $end
$var reg 1 % rst $end
$var integer 32 & test_idx [31:0] $end
$scope module UUT $end
$var wire 1 " clk_i $end
$var wire 5 ' jmp_addr_i [4:0] $end
$var wire 1 $ jmp_en_i $end
$var wire 1 % rst_i $end
$var reg 5 ( addr_o [4:0] $end
$upscope $end
$upscope $end
$enddefinitions $end
#0
$dumpvars
b0 (
b0 '
b0 &
1%
0$
b0 #
1"
b0 !
$end
#5
0"
#10
b1 !
b1 (
1"
0%
b1 &
#15
0"
#20
b10 !
b10 (
1"
b10 &
#25
0"
#30
b11 !
b11 (
1"
b11 &
#35
0"
#40
b11001 !
b11001 (
1"
b11001 #
b11001 '
1$
b100 &
#45
0"
#50
b0 !
b0 (
1"
0$
1%
b101 &
#55
0"
#60
b1 !
b1 (
1"
0%
b110 &
#65
0"
#70
b10 !
b10 (
1"
b111 &
#75
0"
#80
b11 !
b11 (
1"
b1000 &
