src/pc.v
/* 5-bit program counter */

module pc(
  input clk_i,
  input rst_i,
  input jmp_en_i,
  input [4:0] jmp_addr_i,
  output reg [4:0] addr_o
);

  always @(posedge clk_i) begin
    if (rst_i)          addr_o <= 5'b0;
    else if (jmp_en_i)  addr_o <= jmp_addr_i;
    else                addr_o <= addr_o + 1;
  end

endmodule

test/pc_tb.v
`include "src/pc.v"

module pc_tb;

  reg clk = 1'b0;
  reg rst = 1'b0;
  reg jmp_en = 1'b0;
  reg [4:0] jmp_addr = 5'b0;

  wire [4:0] curr_addr;

  integer test_idx = 0;

  pc UUT(
    .clk_i(clk), .rst_i(rst), .jmp_en_i(jmp_en), .jmp_addr_i(jmp_addr),
    .addr_o(curr_addr)
  );

  always begin
    clk = ~clk; #5;
  end

  initial begin
    $dumpfile("bin/pc.vcd");
    $dumpvars(0, pc_tb);

    // Inicio de Señales
    $display("-- Inicia Simulación --");

    // reset
    rst = 1'b1;
    #25; test_idx++;
    $display("%d. Registro PC= %d ",test_idx, curr_addr);

    // inc
    rst = 1'b0;
    #25; test_idx++;
    $display("%d. Registro PC= %d ",test_idx, curr_addr);
    
    // inc
    #25; test_idx++;
    $display("%d. Registro PC= %d ",test_idx, curr_addr);

    // inc
    rst = 1'b0;
    $display("%d. Registro PC= %d ",test_idx, curr_addr);

    // jump
    jmp_en = 1'b1;
    jmp_addr = 5'b11001;  //19h
    #25; test_idx++;  // addr + 1
    $display("%d. Registro PC= %d ",test_idx, curr_addr);

    // reset
    rst = 1'b1;
    #25; test_idx++;
    $display("%d. Registro PC= %d ",test_idx, curr_addr);

    // inc
    rst = 1'b0;
    #25; test_idx++;
    $display("%d . Registro PC= %d ",test_idx, curr_addr);

    // reset
    rst = 1'b1;
    #25; test_idx++;
    $display("%d. Registro PC= %d ",test_idx, curr_addr);

    $finish;
    $display("-- Testbench completed --");

  end

endmodule

bin/pc.vcd
$date
	Mon Jun 10 16:50:04 2024
$end
$version
	Icarus Verilog
$end
$timescale
	1s
$end
$scope module pc_tb $end
$var wire 5 ! curr_addr [4:0] $end
$var reg 1 " clk $end
$var reg 5 # jmp_addr [4:0] $end
$var reg 1 $ jmp_en $end
$var reg 1 % rst $end
$var integer 32 & test_idx [31:0] $end
$scope module UUT $end
$var wire 1 " clk_i $end
$var wire 5 ' jmp_addr_i [4:0] $end
$var wire 1 $ jmp_en_i $end
$var wire 1 % rst_i $end
$var reg 5 ( addr_o [4:0] $end
$upscope $end
$upscope $end
$enddefinitions $end
#0
$dumpvars
b0 (
b0 '
b0 &
1%
0$
b0 #
1"
b0 !
$end
#5
0"
#10
1"
#15
0"
#20
1"
#25
0"
0%
b1 &
#30
b1 !
b1 (
1"
#35
0"
#40
b10 !
b10 (
1"
#45
0"
#50
b11 !
b11 (
1"
b10 &
#55
0"
#60
b100 !
b100 (
1"
#65
0"
#70
b101 !
b101 (
1"
#75
0"
b11 &
#80
b110 !
b110 (
1"
#85
0"
#90
b111 !
b111 (
1"
#95
0"
#100
b11001 !
b11001 (
1"
b11001 #
b11001 '
1$
b100 &
#105
0"
#110
1"
#115
0"
#120
1"
#125
0"
1%
b101 &
#130
b0 !
b0 (
1"
#135
0"
#140
1"
#145
0"
#150
b11001 !
b11001 (
1"
0%
b110 &
#155
0"
#160
1"
#165
0"
#170
1"
#175
0"
1%
b111 &
#180
b0 !
b0 (
1"
#185
0"
#190
1"
#195
0"
#200
1"
b1000 &
