src/ram.v
/* RAM 32x8 - 5-bit addressing, 8-bit word */

module ram(
  input clk_i,
  input wen_i,
  input [7:0] din_i,
  input [4:0] addr_i,
  output [7:0] dout_o
);

  reg [7:0] ram [0:31];
  integer i;
  
  // clear RAM on start
  initial begin
    $display("Loading RAM...");
    //-- Los valores deben estan dados en hexadecimal
    $readmemh("src/data.mem",ram);
  end

  always @(posedge clk_i) begin
    if (wen_i) begin
      ram [addr_i] = din_i;
    end
  end

  assign dout_o = ram [addr_i] ;

endmodule

test/ram_tb.v
`include "src/ram.v"

module ram_tb;
  
  reg clk = 1'b0;
  reg wen = 1'b0;
  reg [7:0] din = 8'b0;
  reg [4:0] addr = 5'b0;

  wire [7:0] dout;

  integer test_idx = 0;

  ram UUT(
    .clk_i(clk), .wen_i(wen), .din_i(din), .addr_i(addr), 
    .dout_o(dout)
  );

  always begin
    clk = ~clk; #5;
  end

  initial begin
    $dumpfile("bin/ram.vcd");
    $dumpvars(0, ram_tb);

  // Inicio de Señales
    $display("-- Inicia Simulación --");
    $display("--------------------------------------------");
    $display("|         Test    Addr   Din   Write   Dout|");
    $display("--------------------------------------------");
  
    #10; test_idx++;
    wen = 0;  // read
    din = 7;
    $display("|%d       %d    %d      %d   %d  |", test_idx, addr, din, wen, dout);


    addr++;  // 1
    #10; test_idx++;
    din = 7;
    $display("|%d       %d    %d      %d   %d  |", test_idx, addr, din, wen, dout);

    wen = 1; // write
    din = 7;
    #10; test_idx++;
    $display("|%d       %d    %d      %d   %d  |", test_idx, addr, din, wen, dout);

    addr++;  // 2
    wen = 0;  // read
    din = 8;
    #10; test_idx++;
    $display("|%d       %d    %d      %d   %d  |", test_idx, addr, din, wen, dout);

    wen = 1;  // write
    #10; test_idx++;
    $display("|%d       %d    %d      %d   %d  |", test_idx, addr, din, wen, dout);

    wen = 0; // read
    #10; test_idx++;
    $display("|%d       %d    %d      %d   %d  |", test_idx, addr, din, wen, dout);

    addr--;  // 1
    #10; test_idx++;
    $display("|%d       %d    %d      %d   %d  |", test_idx, addr, din, wen, dout);

    addr--; // 0
    #10; test_idx++;
    $display("|%d       %d    %d      %d   %d  |", test_idx, addr, din, wen, dout);
  
    $display("--------------------------------------------");

    $display("-- Testbench completed --");
    $finish;
  end

endmodule

bin/ram.vcd
$date
	Fri Jun 14 14:14:15 2024
$end
$version
	Icarus Verilog
$end
$timescale
	1s
$end
$scope module ram_tb $end
$var wire 8 ! dout [7:0] $end
$var reg 5 " addr [4:0] $end
$var reg 1 # clk $end
$var reg 8 $ din [7:0] $end
$var reg 1 % wen $end
$var integer 32 & test_idx [31:0] $end
$scope module UUT $end
$var wire 5 ' addr_i [4:0] $end
$var wire 1 # clk_i $end
$var wire 8 ( din_i [7:0] $end
$var wire 8 ) dout_o [7:0] $end
$var wire 1 % wen_i $end
$upscope $end
$upscope $end
$enddefinitions $end
#0
$dumpvars
b11 )
b0 (
b0 '
b0 &
0%
b0 $
1#
b0 "
b11 !
$end
#5
0#
#10
1#
b10 !
b10 )
b1 "
b1 '
b111 $
b111 (
b1 &
#15
0#
#20
b111 !
b111 )
1#
1%
b10 &
#25
0#
#30
1#
b1000 $
b1000 (
0%
b100 !
b100 )
b10 "
b10 '
b11 &
#35
0#
#40
b1000 !
b1000 )
1#
1%
b100 &
#45
0#
#50
1#
0%
b101 &
#55
0#
#60
1#
b111 !
b111 )
b1 "
b1 '
b110 &
#65
0#
#70
1#
b11 !
b11 )
b0 "
b0 '
b111 &
#75
0#
#80
1#
b1000 &
