src/rom.v
/* Program ROM 32x8 - 5-bit addresses, 8-bit instruction */

module rom(
  input [4:0] addr_i,
  output reg [7:0] data_o
);

  reg [7:0] memory [0:31];

  initial begin
    $display("Loading ROM...");
    $readmemh("src/rom.mem", memory);
  end

  always @(*) begin
    data_o <= memory[addr_i];
  end

endmodule

test/rom_tb.v
`include "src/rom.v"

module rom_tb;
  
  reg [4:0] addr = 5'b0;
  wire [7:0] data = 8'b0;

  integer test_idx = 0;

  rom UUT(.addr_i(addr), .data_o(data));

  initial begin
    $dumpfile("bin/rom.vcd");
    $dumpvars(0, rom_tb);

    for (test_idx = 0; test_idx < 4; test_idx++) begin
      #10;
      addr++;
    end
    
    $display("Testbench completed");
    $finish;

  end

endmodule

bin/rom.vcd
$date
	Mon Jun 10 16:21:59 2024
$end
$version
	Icarus Verilog
$end
$timescale
	1s
$end
$scope module rom_tb $end
$var wire 8 ! data [7:0] $end
$var reg 5 " addr [4:0] $end
$var integer 32 # test_idx [31:0] $end
$scope module UUT $end
$var wire 5 $ addr_i [4:0] $end
$var reg 8 % data_o [7:0] $end
$upscope $end
$upscope $end
$enddefinitions $end
#0
$dumpvars
b1 %
b0 $
b0 #
b0 "
b0x !
$end
#25
b0x000x0 !
b100010 %
b1 #
b1 "
b1 $
#50
b0xx000xx !
b1100011 %
b10 #
b10 "
b10 $
#75
b0 !
b0 %
b11 #
b11 "
b11 $
#100
b100 #
b100 "
b100 $
#125
b101 #
b101 "
b101 $
#150
b110 #
b110 "
b110 $
#175
b111 #
b111 "
b111 $
#200
b1000 #
b1000 "
b1000 $
